llambda/__init__.py
llambda/api.py
llambda/build.py
llambda/complete.py
llambda/llm/__init__.py
llambda/llm/base.py
llambda/llm/openai.py
llambda/model.py
llambda/search.py
llambda/select.py
llambda-0.1.0a1.dist-info/METADATA
llambda-0.1.0a1.dist-info/WHEEL
llambda-0.1.0a1.dist-info/RECORD
