Metadata-Version: 2.1
Name: llambda
Version: 0.1.0a1
Summary: 
Author: Ryuta-Yamamoto
Author-email: 43087138+Ryuta-Yamamoto@users.noreply.github.com
Requires-Python: >=3.9,<4.0
Classifier: Programming Language :: Python :: 3
Classifier: Programming Language :: Python :: 3.9
Classifier: Programming Language :: Python :: 3.10
Classifier: Programming Language :: Python :: 3.11
Requires-Dist: numpy (>=1.24.2,<2.0.0)
Requires-Dist: openai[datalib] (>=0.27.4,<0.28.0)
